jabor/__init__.py
jabor/date_utils.py
jabor-0.0.10.dist-info/LICENSE
jabor-0.0.10.dist-info/METADATA
jabor-0.0.10.dist-info/WHEEL
jabor-0.0.10.dist-info/top_level.txt
jabor-0.0.10.dist-info/RECORD
